flask_cors/__init__.py
flask_cors/core.py
flask_cors/decorator.py
flask_cors/extension.py
flask_cors/version.py
Flask_Cors-4.0.2.dist-info/LICENSE
Flask_Cors-4.0.2.dist-info/METADATA
Flask_Cors-4.0.2.dist-info/WHEEL
Flask_Cors-4.0.2.dist-info/top_level.txt
Flask_Cors-4.0.2.dist-info/RECORD
